{
    "/js/app.js": "/js/app.js",
    "/js/app.2a5a90c3bd1cb86738f7.hot-update.js": "/js/app.2a5a90c3bd1cb86738f7.hot-update.js",
    "/js/app.b28bba94e84db7ed10a8.hot-update.js": "/js/app.b28bba94e84db7ed10a8.hot-update.js",
    "/js/app.9fdefd0c832634a02f03.hot-update.js": "/js/app.9fdefd0c832634a02f03.hot-update.js",
    "/js/app.64c9a91dd011cdf0e4e8.hot-update.js": "/js/app.64c9a91dd011cdf0e4e8.hot-update.js",
    "/js/app.182b53af14130a8e9a7a.hot-update.js": "/js/app.182b53af14130a8e9a7a.hot-update.js",
    "/js/app.ef8829f2bb892153f354.hot-update.js": "/js/app.ef8829f2bb892153f354.hot-update.js",
    "/js/app.67b32703ae4bc8fa0b9c.hot-update.js": "/js/app.67b32703ae4bc8fa0b9c.hot-update.js",
    "/js/app.c28306de08649e149013.hot-update.js": "/js/app.c28306de08649e149013.hot-update.js",
    "/js/app.4061d1da0c9815bd04a2.hot-update.js": "/js/app.4061d1da0c9815bd04a2.hot-update.js",
    "/js/app.33e0bcc28375c73ff825.hot-update.js": "/js/app.33e0bcc28375c73ff825.hot-update.js",
    "/js/app.5851c18d266f9294582f.hot-update.js": "/js/app.5851c18d266f9294582f.hot-update.js",
    "/js/app.59935f68bfda74110ba5.hot-update.js": "/js/app.59935f68bfda74110ba5.hot-update.js",
    "/js/app.babefb77c5941e7e9cc8.hot-update.js": "/js/app.babefb77c5941e7e9cc8.hot-update.js",
    "/js/app.c1fd64d334e29e3afc02.hot-update.js": "/js/app.c1fd64d334e29e3afc02.hot-update.js",
    "/js/app.d9039ebf19c9f8881990.hot-update.js": "/js/app.d9039ebf19c9f8881990.hot-update.js",
    "/js/app.bfbf2f615c6348098149.hot-update.js": "/js/app.bfbf2f615c6348098149.hot-update.js",
    "/js/app.bda62439d5f5b2034f4e.hot-update.js": "/js/app.bda62439d5f5b2034f4e.hot-update.js",
    "/js/app.8287d2b1067fb2aa85ab.hot-update.js": "/js/app.8287d2b1067fb2aa85ab.hot-update.js",
    "/js/app.3ea908a58fef4e2adb27.hot-update.js": "/js/app.3ea908a58fef4e2adb27.hot-update.js",
    "/js/app.2e1138bf4b95ac6492e0.hot-update.js": "/js/app.2e1138bf4b95ac6492e0.hot-update.js",
    "/js/app.cc937aac686574fee1a6.hot-update.js": "/js/app.cc937aac686574fee1a6.hot-update.js",
    "/js/app.d9966172ff9a7d0e90e5.hot-update.js": "/js/app.d9966172ff9a7d0e90e5.hot-update.js",
    "/js/app.962a1cb7fc629f65eadc.hot-update.js": "/js/app.962a1cb7fc629f65eadc.hot-update.js",
    "/js/app.27a7bc052c7efad9e182.hot-update.js": "/js/app.27a7bc052c7efad9e182.hot-update.js",
    "/js/app.5b59cd5d146fb9c67376.hot-update.js": "/js/app.5b59cd5d146fb9c67376.hot-update.js",
    "/js/app.09ee47d127c121dcca8c.hot-update.js": "/js/app.09ee47d127c121dcca8c.hot-update.js",
    "/js/app.4b465c5191ca5a006ae3.hot-update.js": "/js/app.4b465c5191ca5a006ae3.hot-update.js",
    "/js/app.24ecbb974f43b92a8310.hot-update.js": "/js/app.24ecbb974f43b92a8310.hot-update.js",
    "/js/app.b3a146ae773b97d8adc1.hot-update.js": "/js/app.b3a146ae773b97d8adc1.hot-update.js",
    "/js/app.44d2978ab42e16d51c67.hot-update.js": "/js/app.44d2978ab42e16d51c67.hot-update.js",
    "/js/app.e5c0c92efda02646251c.hot-update.js": "/js/app.e5c0c92efda02646251c.hot-update.js",
    "/js/app.e5f3d09678cd1973ea70.hot-update.js": "/js/app.e5f3d09678cd1973ea70.hot-update.js",
    "/js/app.a0b4b44ac1d156073080.hot-update.js": "/js/app.a0b4b44ac1d156073080.hot-update.js",
    "/js/app.4f7c38fe7f2c856c9da3.hot-update.js": "/js/app.4f7c38fe7f2c856c9da3.hot-update.js",
    "/js/app.7ede03e24ca191842ad7.hot-update.js": "/js/app.7ede03e24ca191842ad7.hot-update.js",
    "/js/app.af314ef82d491d2b3e2a.hot-update.js": "/js/app.af314ef82d491d2b3e2a.hot-update.js",
    "/js/app.d59499daa909be9af532.hot-update.js": "/js/app.d59499daa909be9af532.hot-update.js",
    "/js/app.d76cd1f06e8b69785e07.hot-update.js": "/js/app.d76cd1f06e8b69785e07.hot-update.js",
    "/js/app.69b6718bdfc8683acd30.hot-update.js": "/js/app.69b6718bdfc8683acd30.hot-update.js",
    "/js/app.b7935fb61b1f22a80dec.hot-update.js": "/js/app.b7935fb61b1f22a80dec.hot-update.js",
    "/js/app.f9c2e4562627de6b2df4.hot-update.js": "/js/app.f9c2e4562627de6b2df4.hot-update.js",
    "/js/app.872b73236ebebeb5622b.hot-update.js": "/js/app.872b73236ebebeb5622b.hot-update.js",
    "/js/app.f7003303a2886a4be898.hot-update.js": "/js/app.f7003303a2886a4be898.hot-update.js",
    "/js/app.32fa714fe021f13da7e7.hot-update.js": "/js/app.32fa714fe021f13da7e7.hot-update.js",
    "/js/app.7affeff0ab9998a26fdc.hot-update.js": "/js/app.7affeff0ab9998a26fdc.hot-update.js",
    "/js/app.f3a4af06f397b25abd4a.hot-update.js": "/js/app.f3a4af06f397b25abd4a.hot-update.js",
    "/js/app.34c666fecb3e0a6d1cf4.hot-update.js": "/js/app.34c666fecb3e0a6d1cf4.hot-update.js",
    "/js/app.0e8b0f04b584432c261f.hot-update.js": "/js/app.0e8b0f04b584432c261f.hot-update.js",
    "/js/app.3395f9738d4c64befe1e.hot-update.js": "/js/app.3395f9738d4c64befe1e.hot-update.js",
    "/js/app.bafe07779473f681d88b.hot-update.js": "/js/app.bafe07779473f681d88b.hot-update.js",
    "/js/app.1ae34db13f285e9b114b.hot-update.js": "/js/app.1ae34db13f285e9b114b.hot-update.js",
    "/js/app.1dede85911c601674451.hot-update.js": "/js/app.1dede85911c601674451.hot-update.js",
    "/js/app.0de9709dd2adb0e99c41.hot-update.js": "/js/app.0de9709dd2adb0e99c41.hot-update.js",
    "/js/app.623b218879ca8b4da2ec.hot-update.js": "/js/app.623b218879ca8b4da2ec.hot-update.js",
    "/js/app.160d290c1f262447da1e.hot-update.js": "/js/app.160d290c1f262447da1e.hot-update.js",
    "/js/app.be48d83cad9cf8c31cdf.hot-update.js": "/js/app.be48d83cad9cf8c31cdf.hot-update.js",
    "/js/app.0f4805e14dc653d54ec1.hot-update.js": "/js/app.0f4805e14dc653d54ec1.hot-update.js",
    "/js/app.995c9a239a107cbf404a.hot-update.js": "/js/app.995c9a239a107cbf404a.hot-update.js",
    "/js/app.a52cbb389fec3b7c4e43.hot-update.js": "/js/app.a52cbb389fec3b7c4e43.hot-update.js",
    "/js/app.92a0244c1bdb56d36f7e.hot-update.js": "/js/app.92a0244c1bdb56d36f7e.hot-update.js",
    "/js/app.0a4be139368907eae863.hot-update.js": "/js/app.0a4be139368907eae863.hot-update.js",
    "/js/app.0d2334d9655b4d2990e5.hot-update.js": "/js/app.0d2334d9655b4d2990e5.hot-update.js",
    "/js/app.09599d3470b986911d40.hot-update.js": "/js/app.09599d3470b986911d40.hot-update.js",
    "/js/app.c07e1f9cd6f1d580cabc.hot-update.js": "/js/app.c07e1f9cd6f1d580cabc.hot-update.js",
    "/js/app.1b72d624e79467d25405.hot-update.js": "/js/app.1b72d624e79467d25405.hot-update.js",
    "/js/app.4065542d5a7683cecc4f.hot-update.js": "/js/app.4065542d5a7683cecc4f.hot-update.js",
    "/js/app.9efc96420a73bc2d86fc.hot-update.js": "/js/app.9efc96420a73bc2d86fc.hot-update.js",
    "/js/app.e2744181c951b437792f.hot-update.js": "/js/app.e2744181c951b437792f.hot-update.js",
    "/js/app.1e08c952f5ced14228a2.hot-update.js": "/js/app.1e08c952f5ced14228a2.hot-update.js",
    "/js/app.9fab9aa0a21d3db7c174.hot-update.js": "/js/app.9fab9aa0a21d3db7c174.hot-update.js",
    "/js/app.ac800f5e18e1e0d6fe80.hot-update.js": "/js/app.ac800f5e18e1e0d6fe80.hot-update.js",
    "/js/app.1eae6994bc15480f4dd7.hot-update.js": "/js/app.1eae6994bc15480f4dd7.hot-update.js",
    "/js/app.4ffed333ea3428c02a85.hot-update.js": "/js/app.4ffed333ea3428c02a85.hot-update.js",
    "/js/app.089492fa7e96f59b806d.hot-update.js": "/js/app.089492fa7e96f59b806d.hot-update.js",
    "/js/app.a3cd97090613c48814be.hot-update.js": "/js/app.a3cd97090613c48814be.hot-update.js",
    "/js/app.56056af67a7395d33ac0.hot-update.js": "/js/app.56056af67a7395d33ac0.hot-update.js",
    "/js/app.498a8cc48195cf63ad01.hot-update.js": "/js/app.498a8cc48195cf63ad01.hot-update.js",
    "/js/app.00c281fc8e63bb3c296c.hot-update.js": "/js/app.00c281fc8e63bb3c296c.hot-update.js",
    "/js/app.26a41084436e8dab116d.hot-update.js": "/js/app.26a41084436e8dab116d.hot-update.js",
    "/js/app.57ac471464c166f320eb.hot-update.js": "/js/app.57ac471464c166f320eb.hot-update.js",
    "/js/app.4377f303f4946929c860.hot-update.js": "/js/app.4377f303f4946929c860.hot-update.js",
    "/js/app.08f1bed5a2f1f0a47e8f.hot-update.js": "/js/app.08f1bed5a2f1f0a47e8f.hot-update.js",
    "/js/app.f1028b3b442e6b0ae83c.hot-update.js": "/js/app.f1028b3b442e6b0ae83c.hot-update.js",
    "/js/app.b88b002e5a5802114c84.hot-update.js": "/js/app.b88b002e5a5802114c84.hot-update.js",
    "/js/app.d49a80b6dddde0a38d92.hot-update.js": "/js/app.d49a80b6dddde0a38d92.hot-update.js",
    "/js/app.fa7b106190b371094a03.hot-update.js": "/js/app.fa7b106190b371094a03.hot-update.js",
    "/js/app.0a3061a9a30c3400c208.hot-update.js": "/js/app.0a3061a9a30c3400c208.hot-update.js",
    "/js/app.f5f626d9f672b9994636.hot-update.js": "/js/app.f5f626d9f672b9994636.hot-update.js",
    "/js/app.aaa0d4b976324f55cba9.hot-update.js": "/js/app.aaa0d4b976324f55cba9.hot-update.js",
    "/js/app.908ef63d9902f2812708.hot-update.js": "/js/app.908ef63d9902f2812708.hot-update.js",
    "/js/app.30e723feb4e62747cd02.hot-update.js": "/js/app.30e723feb4e62747cd02.hot-update.js",
    "/js/app.f9beab4decebb7547323.hot-update.js": "/js/app.f9beab4decebb7547323.hot-update.js",
    "/js/app.ccd98322a4f04518712c.hot-update.js": "/js/app.ccd98322a4f04518712c.hot-update.js",
    "/js/app.8e25381d6d35d33dd906.hot-update.js": "/js/app.8e25381d6d35d33dd906.hot-update.js",
    "/js/app.58a1abe074e0276e9991.hot-update.js": "/js/app.58a1abe074e0276e9991.hot-update.js",
    "/js/app.dbaa95d81d0861b7ee35.hot-update.js": "/js/app.dbaa95d81d0861b7ee35.hot-update.js",
    "/js/app.c9bf35dd8e26dc15b41f.hot-update.js": "/js/app.c9bf35dd8e26dc15b41f.hot-update.js",
    "/js/app.7b4da7ffe9c4b6ff9d1e.hot-update.js": "/js/app.7b4da7ffe9c4b6ff9d1e.hot-update.js",
    "/js/app.61d8ed32b923db4c9da6.hot-update.js": "/js/app.61d8ed32b923db4c9da6.hot-update.js",
    "/js/app.151ab750afe3e42d9e79.hot-update.js": "/js/app.151ab750afe3e42d9e79.hot-update.js",
    "/js/app.a7f55b1e3751e63887fd.hot-update.js": "/js/app.a7f55b1e3751e63887fd.hot-update.js",
    "/js/app.1f3123f3885553f105be.hot-update.js": "/js/app.1f3123f3885553f105be.hot-update.js",
    "/js/app.3ffdbd9c71b02977ac44.hot-update.js": "/js/app.3ffdbd9c71b02977ac44.hot-update.js",
    "/js/app.904f9bdcb6c4b96abb6a.hot-update.js": "/js/app.904f9bdcb6c4b96abb6a.hot-update.js",
    "/js/app.91b6e84839896909c6fa.hot-update.js": "/js/app.91b6e84839896909c6fa.hot-update.js",
    "/js/app.e970d81ec88a7dfe19e8.hot-update.js": "/js/app.e970d81ec88a7dfe19e8.hot-update.js",
    "/js/app.e2c0bc43c3ab6e40eef3.hot-update.js": "/js/app.e2c0bc43c3ab6e40eef3.hot-update.js",
    "/js/app.39d1d9df9e92db59c8ba.hot-update.js": "/js/app.39d1d9df9e92db59c8ba.hot-update.js",
    "/js/app.d5091167f34c17180465.hot-update.js": "/js/app.d5091167f34c17180465.hot-update.js",
    "/js/app.f263a22e04050c493780.hot-update.js": "/js/app.f263a22e04050c493780.hot-update.js",
    "/js/app.48315777cd25f7d69079.hot-update.js": "/js/app.48315777cd25f7d69079.hot-update.js",
    "/js/app.ad2a2276ceb6e59689b7.hot-update.js": "/js/app.ad2a2276ceb6e59689b7.hot-update.js",
    "/js/app.42e0f1d1eba4db25124b.hot-update.js": "/js/app.42e0f1d1eba4db25124b.hot-update.js"
}
